mgrspy/__init__.py
mgrspy/mgrs.py
mgrspy-0.3.1.dist-info/LICENSE
mgrspy-0.3.1.dist-info/METADATA
mgrspy-0.3.1.dist-info/WHEEL
mgrspy-0.3.1.dist-info/top_level.txt
mgrspy-0.3.1.dist-info/RECORD
